Gen3Save/Gen3Pokemon.py
Gen3Save/Gen3Save.py
Gen3Save/__init__.py
gen3save-0.1.0.dist-info/METADATA
gen3save-0.1.0.dist-info/WHEEL
gen3save-0.1.0.dist-info/top_level.txt
gen3save-0.1.0.dist-info/RECORD
