Metadata-Version: 2.4
Name: Gen3Save
Version: 0.1.0
Summary: Gen3Save è una libreria Python3 per leggere e modificare i salvataggi dei giochi Pokémon di 3a generazione (GBA).
Author: DottSpace12
Author-email: dottspace12@gmail.com
Classifier: Programming Language :: Python :: 3
Classifier: License :: OSI Approved :: MIT License
Classifier: Operating System :: OS Independent
Requires-Python: >=3.6
